code4th/__init__.py
code4th/datasources/__init__.py
code4th/datasources/air4thai.py
code4th_datasource_air4thai-0.2.dist-info/LICENSE
code4th_datasource_air4thai-0.2.dist-info/METADATA
code4th_datasource_air4thai-0.2.dist-info/WHEEL
code4th_datasource_air4thai-0.2.dist-info/top_level.txt
code4th_datasource_air4thai-0.2.dist-info/RECORD
